beatsaver/__init__.py
beatsaver/async_beatsaver.py
beatsaver/base_wrapper.py
beatsaver/beatsaver.py
beatsaver/beatsaver_exceptions.py
beatsaver/models/__init__.py
beatsaver/models/maps.py
beatsaver/models/users.py
beatsaver.py-0.0.1.dist-info/LICENSE
beatsaver.py-0.0.1.dist-info/METADATA
beatsaver.py-0.0.1.dist-info/WHEEL
beatsaver.py-0.0.1.dist-info/top_level.txt
beatsaver.py-0.0.1.dist-info/RECORD
