Metadata-Version: 2.1
Name: beatsaver.py
Version: 0.0.1
Summary: An API wrapper for BeatSaver
Home-page: https://github.com/Sirspam/beatsaver.py
Author: Sirspam
Author-email: xboxclone555@Gmail.com
License: MIT
Keywords: beatsaber,beatsaver,API
Platform: UNKNOWN
Classifier: Programming Language :: Python :: 3
Classifier: License :: OSI Approved :: MIT License
Classifier: Operating System :: OS Independent
Requires-Python: >=3.7
License-File: LICENSE
Requires-Dist: requests
Requires-Dist: aiohttp
Requires-Dist: python-dateutil
